pytidb/__init__.py
pytidb/base.py
pytidb/client.py
pytidb/constants.py
pytidb/errors.py
pytidb/py.typed
pytidb/schema.py
pytidb/search.py
pytidb/table.py
pytidb/utils.py
pytidb/embeddings/__init__.py
pytidb/embeddings/base.py
pytidb/embeddings/litellm.py
pytidb_experimental-0.0.1.dev5.dist-info/METADATA
pytidb_experimental-0.0.1.dev5.dist-info/WHEEL
pytidb_experimental-0.0.1.dev5.dist-info/licenses/LICENSE
pytidb_experimental-0.0.1.dev5.dist-info/RECORD
